{
    "05/02/2009 09:00:00": {
        "Address": "Italy,Rome",
        "Date time": "05/02/2009 09:00:00",
        "Minimum Temperature": "58.9",
        "Maximum Temperature": "76.9",
        "Temperature": "69.7",
        "Dew Point": "51.8",
        "Relative Humidity": "55.11",
        "Heat Index": "",
        "Wind Speed": "7.9",
        "Wind Gust": "",
        "Wind Direction": "241.33",
        "Wind Chill": "",
        "Precipitation": "0.0",
        "Precipitation Cover": "0.0",
        "Snow Depth": "",
        "Visibility": "6.5",
        "Cloud Cover": "13.6",
        "Sea Level Pressure": "",
        "Weather Type": "",
        "Latitude": "41.9032",
        "Longitude": "12.4957",
        "Resolved Address": "Roma, Lazio, Italia",
        "Name": "Roma, Lazio, Italia",
        "Info": "",
        "Conditions": "Clear"
    },
    "05/02/2009 15:00:00": {
        "Address": "Italy,Rome",
        "Date time": "05/02/2009 15:00:00",
        "Minimum Temperature": "66.1",
        "Maximum Temperature": "69.4",
        "Temperature": "67.7",
        "Dew Point": "49.2",
        "Relative Humidity": "51.64",
        "Heat Index": "",
        "Wind Speed": "14.0",
        "Wind Gust": "",
        "Wind Direction": "172.83",
        "Wind Chill": "",
        "Precipitation": "0.0",
        "Precipitation Cover": "0.0",
        "Snow Depth": "",
        "Visibility": "6.8",
        "Cloud Cover": "49.1",
        "Sea Level Pressure": "",
        "Weather Type": "",
        "Latitude": "41.9032",
        "Longitude": "12.4957",
        "Resolved Address": "Roma, Lazio, Italia",
        "Name": "Roma, Lazio, Italia",
        "Info": "",
        "Conditions": "Partially cloudy"
    },
    "05/02/2009 21:00:00": {
        "Address": "Italy,Rome",
        "Date time": "05/02/2009 21:00:00",
        "Minimum Temperature": "55.5",
        "Maximum Temperature": "62.5",
        "Temperature": "58.2",
        "Dew Point": "49.0",
        "Relative Humidity": "71.9",
        "Heat Index": "",
        "Wind Speed": "8.1",
        "Wind Gust": "",
        "Wind Direction": "36.67",
        "Wind Chill": "",
        "Precipitation": "0.0",
        "Precipitation Cover": "0.0",
        "Snow Depth": "",
        "Visibility": "6.8",
        "Cloud Cover": "50.0",
        "Sea Level Pressure": "",
        "Weather Type": "",
        "Latitude": "41.9032",
        "Longitude": "12.4957",
        "Resolved Address": "Roma, Lazio, Italia",
        "Name": "Roma, Lazio, Italia",
        "Info": "",
        "Conditions": "Partially cloudy"
    },
    "05/03/2009 09:00:00": {
        "Address": "Italy,Rome",
        "Date time": "05/03/2009 09:00:00",
        "Minimum Temperature": "60.7",
        "Maximum Temperature": "69.7",
        "Temperature": "65.1",
        "Dew Point": "42.0",
        "Relative Humidity": "43.52",
        "Heat Index": "",
        "Wind Speed": "19.2",
        "Wind Gust": "",
        "Wind Direction": "200.33",
        "Wind Chill": "",
        "Precipitation": "0.0",
        "Precipitation Cover": "0.0",
        "Snow Depth": "",
        "Visibility": "6.6",
        "Cloud Cover": "24.0",
        "Sea Level Pressure": "",
        "Weather Type": "",
        "Latitude": "41.9032",
        "Longitude": "12.4957",
        "Resolved Address": "Roma, Lazio, Italia",
        "Name": "Roma, Lazio, Italia",
        "Info": "",
        "Conditions": "Clear"
    },
    "05/03/2009 15:00:00": {
        "Address": "Italy,Rome",
        "Date time": "05/03/2009 15:00:00",
        "Minimum Temperature": "63.6",
        "Maximum Temperature": "69.4",
        "Temperature": "66.9",
        "Dew Point": "40.7",
        "Relative Humidity": "38.46",
        "Heat Index": "",
        "Wind Speed": "17.6",
        "Wind Gust": "",
        "Wind Direction": "233.67",
        "Wind Chill": "",
        "Precipitation": "0.0",
        "Precipitation Cover": "0.0",
        "Snow Depth": "",
        "Visibility": "6.8",
        "Cloud Cover": "33.0",
        "Sea Level Pressure": "",
        "Weather Type": "",
        "Latitude": "41.9032",
        "Longitude": "12.4957",
        "Resolved Address": "Roma, Lazio, Italia",
        "Name": "Roma, Lazio, Italia",
        "Info": "",
        "Conditions": "Partially cloudy"
    },
    "05/03/2009 21:00:00": {
        "Address": "Italy,Rome",
        "Date time": "05/03/2009 21:00:00",
        "Minimum Temperature": "48.3",
        "Maximum Temperature": "60.0",
        "Temperature": "51.7",
        "Dew Point": "44.9",
        "Relative Humidity": "79.5",
        "Heat Index": "",
        "Wind Speed": "7.3",
        "Wind Gust": "",
        "Wind Direction": "102.8",
        "Wind Chill": "",
        "Precipitation": "0.0",
        "Precipitation Cover": "0.0",
        "Snow Depth": "",
        "Visibility": "6.5",
        "Cloud Cover": "15.0",
        "Sea Level Pressure": "",
        "Weather Type": "",
        "Latitude": "41.9032",
        "Longitude": "12.4957",
        "Resolved Address": "Roma, Lazio, Italia",
        "Name": "Roma, Lazio, Italia",
        "Info": "",
        "Conditions": "Clear"
    },
    "05/04/2009 09:00:00": {
        "Address": "Italy,Rome",
        "Date time": "05/04/2009 09:00:00",
        "Minimum Temperature": "58.9",
        "Maximum Temperature": "74.8",
        "Temperature": "67.9",
        "Dew Point": "48.3",
        "Relative Humidity": "50.87",
        "Heat Index": "",
        "Wind Speed": "4.0",
        "Wind Gust": "",
        "Wind Direction": "203.0",
        "Wind Chill": "",
        "Precipitation": "0.0",
        "Precipitation Cover": "0.0",
        "Snow Depth": "",
        "Visibility": "6.4",
        "Cloud Cover": "11.7",
        "Sea Level Pressure": "",
        "Weather Type": "",
        "Latitude": "41.9032",
        "Longitude": "12.4957",
        "Resolved Address": "Roma, Lazio, Italia",
        "Name": "Roma, Lazio, Italia",
        "Info": "",
        "Conditions": "Clear"
    },
    "05/04/2009 15:00:00": {
        "Address": "Italy,Rome",
        "Date time": "05/04/2009 15:00:00",
        "Minimum Temperature": "65.8",
        "Maximum Temperature": "71.7",
        "Temperature": "69.1",
        "Dew Point": "49.0",
        "Relative Humidity": "48.85",
        "Heat Index": "",
        "Wind Speed": "13.6",
        "Wind Gust": "",
        "Wind Direction": "239.83",
        "Wind Chill": "",
        "Precipitation": "0.0",
        "Precipitation Cover": "0.0",
        "Snow Depth": "",
        "Visibility": "6.8",
        "Cloud Cover": "34.6",
        "Sea Level Pressure": "",
        "Weather Type": "",
        "Latitude": "41.9032",
        "Longitude": "12.4957",
        "Resolved Address": "Roma, Lazio, Italia",
        "Name": "Roma, Lazio, Italia",
        "Info": "",
        "Conditions": "Partially cloudy"
    },
    "05/04/2009 21:00:00": {
        "Address": "Italy,Rome",
        "Date time": "05/04/2009 21:00:00",
        "Minimum Temperature": "57.3",
        "Maximum Temperature": "60.9",
        "Temperature": "58.8",
        "Dew Point": "51.9",
        "Relative Humidity": "78.64",
        "Heat Index": "",
        "Wind Speed": "5.8",
        "Wind Gust": "",
        "Wind Direction": "176.67",
        "Wind Chill": "",
        "Precipitation": "0.0",
        "Precipitation Cover": "0.0",
        "Snow Depth": "",
        "Visibility": "6.5",
        "Cloud Cover": "21.7",
        "Sea Level Pressure": "",
        "Weather Type": "",
        "Latitude": "41.9032",
        "Longitude": "12.4957",
        "Resolved Address": "Roma, Lazio, Italia",
        "Name": "Roma, Lazio, Italia",
        "Info": "",
        "Conditions": "Clear"
    },
    "05/05/2009 09:00:00": {
        "Address": "Italy,Rome",
        "Date time": "05/05/2009 09:00:00",
        "Minimum Temperature": "60.9",
        "Maximum Temperature": "71.5",
        "Temperature": "66.9",
        "Dew Point": "53.2",
        "Relative Humidity": "61.83",
        "Heat Index": "",
        "Wind Speed": "8.2",
        "Wind Gust": "",
        "Wind Direction": "240.67",
        "Wind Chill": "",
        "Precipitation": "0.0",
        "Precipitation Cover": "0.0",
        "Snow Depth": "",
        "Visibility": "6.5",
        "Cloud Cover": "18.0",
        "Sea Level Pressure": "",
        "Weather Type": "",
        "Latitude": "41.9032",
        "Longitude": "12.4957",
        "Resolved Address": "Roma, Lazio, Italia",
        "Name": "Roma, Lazio, Italia",
        "Info": "",
        "Conditions": "Clear"
    },
    "05/05/2009 15:00:00": {
        "Address": "Italy,Rome",
        "Date time": "05/05/2009 15:00:00",
        "Minimum Temperature": "59.1",
        "Maximum Temperature": "66.5",
        "Temperature": "62.3",
        "Dew Point": "52.7",
        "Relative Humidity": "71.53",
        "Heat Index": "",
        "Wind Speed": "16.2",
        "Wind Gust": "",
        "Wind Direction": "161.0",
        "Wind Chill": "",
        "Precipitation": "0.16",
        "Precipitation Cover": "16.67",
        "Snow Depth": "",
        "Visibility": "6.8",
        "Cloud Cover": "53.8",
        "Sea Level Pressure": "",
        "Weather Type": "",
        "Latitude": "41.9032",
        "Longitude": "12.4957",
        "Resolved Address": "Roma, Lazio, Italia",
        "Name": "Roma, Lazio, Italia",
        "Info": "",
        "Conditions": "Rain, Partially cloudy"
    },
    "05/05/2009 21:00:00": {
        "Address": "Italy,Rome",
        "Date time": "05/05/2009 21:00:00",
        "Minimum Temperature": "51.9",
        "Maximum Temperature": "57.5",
        "Temperature": "54.6",
        "Dew Point": "52.4",
        "Relative Humidity": "92.55",
        "Heat Index": "",
        "Wind Speed": "3.4",
        "Wind Gust": "",
        "Wind Direction": "25.0",
        "Wind Chill": "",
        "Precipitation": "0.0",
        "Precipitation Cover": "0.0",
        "Snow Depth": "",
        "Visibility": "6.3",
        "Cloud Cover": "5.0",
        "Sea Level Pressure": "",
        "Weather Type": "",
        "Latitude": "41.9032",
        "Longitude": "12.4957",
        "Resolved Address": "Roma, Lazio, Italia",
        "Name": "Roma, Lazio, Italia",
        "Info": "",
        "Conditions": "Clear"
    },
    "05/06/2009 09:00:00": {
        "Address": "Italy,Rome",
        "Date time": "05/06/2009 09:00:00",
        "Minimum Temperature": "54.4",
        "Maximum Temperature": "73.3",
        "Temperature": "65.2",
        "Dew Point": "53.5",
        "Relative Humidity": "67.89",
        "Heat Index": "",
        "Wind Speed": "3.4",
        "Wind Gust": "",
        "Wind Direction": "297.0",
        "Wind Chill": "",
        "Precipitation": "0.0",
        "Precipitation Cover": "0.0",
        "Snow Depth": "",
        "Visibility": "5.6",
        "Cloud Cover": "20.3",
        "Sea Level Pressure": "",
        "Weather Type": "",
        "Latitude": "41.9032",
        "Longitude": "12.4957",
        "Resolved Address": "Roma, Lazio, Italia",
        "Name": "Roma, Lazio, Italia",
        "Info": "",
        "Conditions": "Clear"
    },
    "05/06/2009 15:00:00": {
        "Address": "Italy,Rome",
        "Date time": "05/06/2009 15:00:00",
        "Minimum Temperature": "64.0",
        "Maximum Temperature": "71.5",
        "Temperature": "68.1",
        "Dew Point": "52.4",
        "Relative Humidity": "57.4",
        "Heat Index": "",
        "Wind Speed": "13.3",
        "Wind Gust": "",
        "Wind Direction": "255.17",
        "Wind Chill": "",
        "Precipitation": "0.0",
        "Precipitation Cover": "0.0",
        "Snow Depth": "",
        "Visibility": "6.7",
        "Cloud Cover": "26.7",
        "Sea Level Pressure": "",
        "Weather Type": "",
        "Latitude": "41.9032",
        "Longitude": "12.4957",
        "Resolved Address": "Roma, Lazio, Italia",
        "Name": "Roma, Lazio, Italia",
        "Info": "",
        "Conditions": "Partially cloudy"
    },
    "05/06/2009 21:00:00": {
        "Address": "Italy,Rome",
        "Date time": "05/06/2009 21:00:00",
        "Minimum Temperature": "55.5",
        "Maximum Temperature": "62.5",
        "Temperature": "58.8",
        "Dew Point": "52.8",
        "Relative Humidity": "81.18",
        "Heat Index": "",
        "Wind Speed": "4.7",
        "Wind Gust": "",
        "Wind Direction": "181.67",
        "Wind Chill": "",
        "Precipitation": "0.0",
        "Precipitation Cover": "0.0",
        "Snow Depth": "",
        "Visibility": "6.6",
        "Cloud Cover": "30.0",
        "Sea Level Pressure": "",
        "Weather Type": "",
        "Latitude": "41.9032",
        "Longitude": "12.4957",
        "Resolved Address": "Roma, Lazio, Italia",
        "Name": "Roma, Lazio, Italia",
        "Info": "",
        "Conditions": "Partially cloudy"
    },
    "05/07/2009 09:00:00": {
        "Address": "Italy,Rome",
        "Date time": "05/07/2009 09:00:00",
        "Minimum Temperature": "61.3",
        "Maximum Temperature": "76.6",
        "Temperature": "70.3",
        "Dew Point": "55.7",
        "Relative Humidity": "61.71",
        "Heat Index": "",
        "Wind Speed": "4.7",
        "Wind Gust": "",
        "Wind Direction": "218.33",
        "Wind Chill": "",
        "Precipitation": "0.0",
        "Precipitation Cover": "0.0",
        "Snow Depth": "",
        "Visibility": "6.5",
        "Cloud Cover": "11.9",
        "Sea Level Pressure": "",
        "Weather Type": "",
        "Latitude": "41.9032",
        "Longitude": "12.4957",
        "Resolved Address": "Roma, Lazio, Italia",
        "Name": "Roma, Lazio, Italia",
        "Info": "",
        "Conditions": "Clear"
    },
    "05/07/2009 15:00:00": {
        "Address": "Italy,Rome",
        "Date time": "05/07/2009 15:00:00",
        "Minimum Temperature": "67.9",
        "Maximum Temperature": "75.1",
        "Temperature": "72.6",
        "Dew Point": "53.4",
        "Relative Humidity": "50.95",
        "Heat Index": "",
        "Wind Speed": "9.9",
        "Wind Gust": "",
        "Wind Direction": "230.5",
        "Wind Chill": "",
        "Precipitation": "0.0",
        "Precipitation Cover": "0.0",
        "Snow Depth": "",
        "Visibility": "6.5",
        "Cloud Cover": "11.9",
        "Sea Level Pressure": "",
        "Weather Type": "",
        "Latitude": "41.9032",
        "Longitude": "12.4957",
        "Resolved Address": "Roma, Lazio, Italia",
        "Name": "Roma, Lazio, Italia",
        "Info": "",
        "Conditions": "Clear"
    },
    "05/07/2009 21:00:00": {
        "Address": "Italy,Rome",
        "Date time": "05/07/2009 21:00:00",
        "Minimum Temperature": "57.3",
        "Maximum Temperature": "64.3",
        "Temperature": "60.6",
        "Dew Point": "48.2",
        "Relative Humidity": "64.04",
        "Heat Index": "",
        "Wind Speed": "4.7",
        "Wind Gust": "",
        "Wind Direction": "171.0",
        "Wind Chill": "",
        "Precipitation": "0.0",
        "Precipitation Cover": "0.0",
        "Snow Depth": "",
        "Visibility": "6.2",
        "Cloud Cover": "0.0",
        "Sea Level Pressure": "",
        "Weather Type": "",
        "Latitude": "41.9032",
        "Longitude": "12.4957",
        "Resolved Address": "Roma, Lazio, Italia",
        "Name": "Roma, Lazio, Italia",
        "Info": "",
        "Conditions": "Clear"
    },
    "05/08/2009 09:00:00": {
        "Address": "Italy,Rome",
        "Date time": "05/08/2009 09:00:00",
        "Minimum Temperature": "59.5",
        "Maximum Temperature": "73.5",
        "Temperature": "69.1",
        "Dew Point": "51.5",
        "Relative Humidity": "55.25",
        "Heat Index": "",
        "Wind Speed": "10.3",
        "Wind Gust": "",
        "Wind Direction": "247.4",
        "Wind Chill": "",
        "Precipitation": "0.0",
        "Precipitation Cover": "0.0",
        "Snow Depth": "",
        "Visibility": "6.3",
        "Cloud Cover": "4.9",
        "Sea Level Pressure": "",
        "Weather Type": "",
        "Latitude": "41.9032",
        "Longitude": "12.4957",
        "Resolved Address": "Roma, Lazio, Italia",
        "Name": "Roma, Lazio, Italia",
        "Info": "",
        "Conditions": "Clear"
    },
    "05/08/2009 15:00:00": {
        "Address": "Italy,Rome",
        "Date time": "05/08/2009 15:00:00",
        "Minimum Temperature": "66.3",
        "Maximum Temperature": "73.3",
        "Temperature": "71.5",
        "Dew Point": "50.7",
        "Relative Humidity": "47.97",
        "Heat Index": "",
        "Wind Speed": "7.5",
        "Wind Gust": "",
        "Wind Direction": "234.5",
        "Wind Chill": "",
        "Precipitation": "0.0",
        "Precipitation Cover": "0.0",
        "Snow Depth": "",
        "Visibility": "6.3",
        "Cloud Cover": "1.9",
        "Sea Level Pressure": "",
        "Weather Type": "",
        "Latitude": "41.9032",
        "Longitude": "12.4957",
        "Resolved Address": "Roma, Lazio, Italia",
        "Name": "Roma, Lazio, Italia",
        "Info": "",
        "Conditions": "Clear"
    },
    "05/08/2009 21:00:00": {
        "Address": "Italy,Rome",
        "Date time": "05/08/2009 21:00:00",
        "Minimum Temperature": "55.5",
        "Maximum Temperature": "64.0",
        "Temperature": "58.7",
        "Dew Point": "49.9",
        "Relative Humidity": "72.96",
        "Heat Index": "",
        "Wind Speed": "4.7",
        "Wind Gust": "",
        "Wind Direction": "139.2",
        "Wind Chill": "",
        "Precipitation": "0.0",
        "Precipitation Cover": "0.0",
        "Snow Depth": "",
        "Visibility": "6.2",
        "Cloud Cover": "0.6",
        "Sea Level Pressure": "",
        "Weather Type": "",
        "Latitude": "41.9032",
        "Longitude": "12.4957",
        "Resolved Address": "Roma, Lazio, Italia",
        "Name": "Roma, Lazio, Italia",
        "Info": "",
        "Conditions": "Clear"
    },
    "05/09/2009 09:00:00": {
        "Address": "Italy,Rome",
        "Date time": "05/09/2009 09:00:00",
        "Minimum Temperature": "59.5",
        "Maximum Temperature": "76.6",
        "Temperature": "69.9",
        "Dew Point": "51.2",
        "Relative Humidity": "53.35",
        "Heat Index": "",
        "Wind Speed": "7.1",
        "Wind Gust": "",
        "Wind Direction": "222.17",
        "Wind Chill": "",
        "Precipitation": "0.0",
        "Precipitation Cover": "0.0",
        "Snow Depth": "",
        "Visibility": "6.3",
        "Cloud Cover": "4.0",
        "Sea Level Pressure": "",
        "Weather Type": "",
        "Latitude": "41.9032",
        "Longitude": "12.4957",
        "Resolved Address": "Roma, Lazio, Italia",
        "Name": "Roma, Lazio, Italia",
        "Info": "",
        "Conditions": "Clear"
    },
    "05/09/2009 15:00:00": {
        "Address": "Italy,Rome",
        "Date time": "05/09/2009 15:00:00",
        "Minimum Temperature": "67.9",
        "Maximum Temperature": "75.1",
        "Temperature": "72.1",
        "Dew Point": "49.2",
        "Relative Humidity": "44.7",
        "Heat Index": "",
        "Wind Speed": "10.0",
        "Wind Gust": "",
        "Wind Direction": "238.0",
        "Wind Chill": "",
        "Precipitation": "0.0",
        "Precipitation Cover": "0.0",
        "Snow Depth": "",
        "Visibility": "6.3",
        "Cloud Cover": "6.0",
        "Sea Level Pressure": "",
        "Weather Type": "",
        "Latitude": "41.9032",
        "Longitude": "12.4957",
        "Resolved Address": "Roma, Lazio, Italia",
        "Name": "Roma, Lazio, Italia",
        "Info": "",
        "Conditions": "Clear"
    },
    "05/09/2009 21:00:00": {
        "Address": "Italy,Rome",
        "Date time": "05/09/2009 21:00:00",
        "Minimum Temperature": "57.3",
        "Maximum Temperature": "64.5",
        "Temperature": "60.0",
        "Dew Point": "50.8",
        "Relative Humidity": "72.25",
        "Heat Index": "",
        "Wind Speed": "3.1",
        "Wind Gust": "",
        "Wind Direction": "113.4",
        "Wind Chill": "",
        "Precipitation": "0.0",
        "Precipitation Cover": "0.0",
        "Snow Depth": "",
        "Visibility": "6.2",
        "Cloud Cover": "1.1",
        "Sea Level Pressure": "",
        "Weather Type": "",
        "Latitude": "41.9032",
        "Longitude": "12.4957",
        "Resolved Address": "Roma, Lazio, Italia",
        "Name": "Roma, Lazio, Italia",
        "Info": "",
        "Conditions": "Clear"
    },
    "05/10/2009 09:00:00": {
        "Address": "Italy,Rome",
        "Date time": "05/10/2009 09:00:00",
        "Minimum Temperature": "61.3",
        "Maximum Temperature": "78.7",
        "Temperature": "71.8",
        "Dew Point": "49.7",
        "Relative Humidity": "48.15",
        "Heat Index": "",
        "Wind Speed": "6.4",
        "Wind Gust": "",
        "Wind Direction": "177.0",
        "Wind Chill": "",
        "Precipitation": "0.0",
        "Precipitation Cover": "0.0",
        "Snow Depth": "",
        "Visibility": "6.3",
        "Cloud Cover": "4.3",
        "Sea Level Pressure": "",
        "Weather Type": "",
        "Latitude": "41.9032",
        "Longitude": "12.4957",
        "Resolved Address": "Roma, Lazio, Italia",
        "Name": "Roma, Lazio, Italia",
        "Info": "",
        "Conditions": "Clear"
    },
    "05/10/2009 15:00:00": {
        "Address": "Italy,Rome",
        "Date time": "05/10/2009 15:00:00",
        "Minimum Temperature": "69.7",
        "Maximum Temperature": "78.7",
        "Temperature": "75.6",
        "Dew Point": "46.8",
        "Relative Humidity": "36.24",
        "Heat Index": "",
        "Wind Speed": "11.3",
        "Wind Gust": "",
        "Wind Direction": "260.83",
        "Wind Chill": "",
        "Precipitation": "0.0",
        "Precipitation Cover": "0.0",
        "Snow Depth": "",
        "Visibility": "6.3",
        "Cloud Cover": "3.2",
        "Sea Level Pressure": "",
        "Weather Type": "",
        "Latitude": "41.9032",
        "Longitude": "12.4957",
        "Resolved Address": "Roma, Lazio, Italia",
        "Name": "Roma, Lazio, Italia",
        "Info": "",
        "Conditions": "Clear"
    },
    "05/10/2009 21:00:00": {
        "Address": "Italy,Rome",
        "Date time": "05/10/2009 21:00:00",
        "Minimum Temperature": "57.3",
        "Maximum Temperature": "66.1",
        "Temperature": "60.6",
        "Dew Point": "48.4",
        "Relative Humidity": "65.01",
        "Heat Index": "",
        "Wind Speed": "2.9",
        "Wind Gust": "",
        "Wind Direction": "145.0",
        "Wind Chill": "",
        "Precipitation": "0.0",
        "Precipitation Cover": "0.0",
        "Snow Depth": "",
        "Visibility": "6.2",
        "Cloud Cover": "0.0",
        "Sea Level Pressure": "",
        "Weather Type": "",
        "Latitude": "41.9032",
        "Longitude": "12.4957",
        "Resolved Address": "Roma, Lazio, Italia",
        "Name": "Roma, Lazio, Italia",
        "Info": "",
        "Conditions": "Clear"
    },
    "05/11/2009 09:00:00": {
        "Address": "Italy,Rome",
        "Date time": "05/11/2009 09:00:00",
        "Minimum Temperature": "61.8",
        "Maximum Temperature": "80.5",
        "Temperature": "73.7",
        "Dew Point": "49.8",
        "Relative Humidity": "45.2",
        "Heat Index": "79.5",
        "Wind Speed": "8.1",
        "Wind Gust": "",
        "Wind Direction": "229.5",
        "Wind Chill": "",
        "Precipitation": "0.0",
        "Precipitation Cover": "0.0",
        "Snow Depth": "",
        "Visibility": "6.2",
        "Cloud Cover": "1.3",
        "Sea Level Pressure": "",
        "Weather Type": "",
        "Latitude": "41.9032",
        "Longitude": "12.4957",
        "Resolved Address": "Roma, Lazio, Italia",
        "Name": "Roma, Lazio, Italia",
        "Info": "",
        "Conditions": "Clear"
    },
    "05/11/2009 15:00:00": {
        "Address": "Italy,Rome",
        "Date time": "05/11/2009 15:00:00",
        "Minimum Temperature": "71.7",
        "Maximum Temperature": "78.9",
        "Temperature": "76.9",
        "Dew Point": "42.2",
        "Relative Humidity": "29.08",
        "Heat Index": "",
        "Wind Speed": "7.5",
        "Wind Gust": "",
        "Wind Direction": "262.83",
        "Wind Chill": "",
        "Precipitation": "0.0",
        "Precipitation Cover": "0.0",
        "Snow Depth": "",
        "Visibility": "6.3",
        "Cloud Cover": "5.0",
        "Sea Level Pressure": "",
        "Weather Type": "",
        "Latitude": "41.9032",
        "Longitude": "12.4957",
        "Resolved Address": "Roma, Lazio, Italia",
        "Name": "Roma, Lazio, Italia",
        "Info": "",
        "Conditions": "Clear"
    },
    "05/11/2009 21:00:00": {
        "Address": "Italy,Rome",
        "Date time": "05/11/2009 21:00:00",
        "Minimum Temperature": "59.1",
        "Maximum Temperature": "69.4",
        "Temperature": "63.7",
        "Dew Point": "48.6",
        "Relative Humidity": "58.54",
        "Heat Index": "",
        "Wind Speed": "2.9",
        "Wind Gust": "",
        "Wind Direction": "140.0",
        "Wind Chill": "",
        "Precipitation": "0.0",
        "Precipitation Cover": "0.0",
        "Snow Depth": "",
        "Visibility": "6.2",
        "Cloud Cover": "0.0",
        "Sea Level Pressure": "",
        "Weather Type": "",
        "Latitude": "41.9032",
        "Longitude": "12.4957",
        "Resolved Address": "Roma, Lazio, Italia",
        "Name": "Roma, Lazio, Italia",
        "Info": "",
        "Conditions": "Clear"
    },
    "05/12/2009 09:00:00": {
        "Address": "Italy,Rome",
        "Date time": "05/12/2009 09:00:00",
        "Minimum Temperature": "61.6",
        "Maximum Temperature": "80.7",
        "Temperature": "74.0",
        "Dew Point": "49.9",
        "Relative Humidity": "45.43",
        "Heat Index": "79.4",
        "Wind Speed": "4.7",
        "Wind Gust": "",
        "Wind Direction": "206.33",
        "Wind Chill": "",
        "Precipitation": "0.0",
        "Precipitation Cover": "0.0",
        "Snow Depth": "",
        "Visibility": "6.2",
        "Cloud Cover": "0.0",
        "Sea Level Pressure": "",
        "Weather Type": "",
        "Latitude": "41.9032",
        "Longitude": "12.4957",
        "Resolved Address": "Roma, Lazio, Italia",
        "Name": "Roma, Lazio, Italia",
        "Info": "",
        "Conditions": "Clear"
    },
    "05/12/2009 15:00:00": {
        "Address": "Italy,Rome",
        "Date time": "05/12/2009 15:00:00",
        "Minimum Temperature": "72.8",
        "Maximum Temperature": "80.7",
        "Temperature": "78.0",
        "Dew Point": "46.9",
        "Relative Humidity": "33.73",
        "Heat Index": "79.8",
        "Wind Speed": "9.7",
        "Wind Gust": "",
        "Wind Direction": "249.83",
        "Wind Chill": "",
        "Precipitation": "0.0",
        "Precipitation Cover": "0.0",
        "Snow Depth": "",
        "Visibility": "6.2",
        "Cloud Cover": "0.0",
        "Sea Level Pressure": "",
        "Weather Type": "",
        "Latitude": "41.9032",
        "Longitude": "12.4957",
        "Resolved Address": "Roma, Lazio, Italia",
        "Name": "Roma, Lazio, Italia",
        "Info": "",
        "Conditions": "Clear"
    },
    "05/12/2009 21:00:00": {
        "Address": "Italy,Rome",
        "Date time": "05/12/2009 21:00:00",
        "Minimum Temperature": "59.1",
        "Maximum Temperature": "67.9",
        "Temperature": "63.0",
        "Dew Point": "55.6",
        "Relative Humidity": "77.85",
        "Heat Index": "",
        "Wind Speed": "4.5",
        "Wind Gust": "",
        "Wind Direction": "118.8",
        "Wind Chill": "",
        "Precipitation": "0.0",
        "Precipitation Cover": "0.0",
        "Snow Depth": "",
        "Visibility": "6.2",
        "Cloud Cover": "0.0",
        "Sea Level Pressure": "",
        "Weather Type": "",
        "Latitude": "41.9032",
        "Longitude": "12.4957",
        "Resolved Address": "Roma, Lazio, Italia",
        "Name": "Roma, Lazio, Italia",
        "Info": "",
        "Conditions": "Clear"
    },
    "05/13/2009 09:00:00": {
        "Address": "Italy,Rome",
        "Date time": "05/13/2009 09:00:00",
        "Minimum Temperature": "61.8",
        "Maximum Temperature": "80.7",
        "Temperature": "73.3",
        "Dew Point": "50.6",
        "Relative Humidity": "46.92",
        "Heat Index": "79.8",
        "Wind Speed": "5.3",
        "Wind Gust": "",
        "Wind Direction": "219.0",
        "Wind Chill": "",
        "Precipitation": "0.0",
        "Precipitation Cover": "0.0",
        "Snow Depth": "",
        "Visibility": "6.2",
        "Cloud Cover": "0.0",
        "Sea Level Pressure": "",
        "Weather Type": "",
        "Latitude": "41.9032",
        "Longitude": "12.4957",
        "Resolved Address": "Roma, Lazio, Italia",
        "Name": "Roma, Lazio, Italia",
        "Info": "",
        "Conditions": "Clear"
    },
    "05/13/2009 15:00:00": {
        "Address": "Italy,Rome",
        "Date time": "05/13/2009 15:00:00",
        "Minimum Temperature": "73.3",
        "Maximum Temperature": "82.3",
        "Temperature": "78.6",
        "Dew Point": "48.7",
        "Relative Humidity": "35.18",
        "Heat Index": "81.1",
        "Wind Speed": "11.1",
        "Wind Gust": "",
        "Wind Direction": "238.5",
        "Wind Chill": "",
        "Precipitation": "0.0",
        "Precipitation Cover": "0.0",
        "Snow Depth": "",
        "Visibility": "6.2",
        "Cloud Cover": "0.0",
        "Sea Level Pressure": "",
        "Weather Type": "",
        "Latitude": "41.9032",
        "Longitude": "12.4957",
        "Resolved Address": "Roma, Lazio, Italia",
        "Name": "Roma, Lazio, Italia",
        "Info": "",
        "Conditions": "Clear"
    },
    "05/13/2009 21:00:00": {
        "Address": "Italy,Rome",
        "Date time": "05/13/2009 21:00:00",
        "Minimum Temperature": "60.9",
        "Maximum Temperature": "69.7",
        "Temperature": "64.4",
        "Dew Point": "53.5",
        "Relative Humidity": "68.64",
        "Heat Index": "",
        "Wind Speed": "5.8",
        "Wind Gust": "",
        "Wind Direction": "162.25",
        "Wind Chill": "",
        "Precipitation": "0.0",
        "Precipitation Cover": "0.0",
        "Snow Depth": "",
        "Visibility": "6.2",
        "Cloud Cover": "0.0",
        "Sea Level Pressure": "",
        "Weather Type": "",
        "Latitude": "41.9032",
        "Longitude": "12.4957",
        "Resolved Address": "Roma, Lazio, Italia",
        "Name": "Roma, Lazio, Italia",
        "Info": "",
        "Conditions": "Clear"
    },
    "05/14/2009 09:00:00": {
        "Address": "Italy,Rome",
        "Date time": "05/14/2009 09:00:00",
        "Minimum Temperature": "63.8",
        "Maximum Temperature": "80.5",
        "Temperature": "74.7",
        "Dew Point": "51.5",
        "Relative Humidity": "46.35",
        "Heat Index": "79.9",
        "Wind Speed": "9.2",
        "Wind Gust": "",
        "Wind Direction": "233.2",
        "Wind Chill": "",
        "Precipitation": "0.0",
        "Precipitation Cover": "0.0",
        "Snow Depth": "",
        "Visibility": "6.3",
        "Cloud Cover": "5.7",
        "Sea Level Pressure": "",
        "Weather Type": "",
        "Latitude": "41.9032",
        "Longitude": "12.4957",
        "Resolved Address": "Roma, Lazio, Italia",
        "Name": "Roma, Lazio, Italia",
        "Info": "",
        "Conditions": "Clear"
    },
    "05/14/2009 15:00:00": {
        "Address": "Italy,Rome",
        "Date time": "05/14/2009 15:00:00",
        "Minimum Temperature": "73.3",
        "Maximum Temperature": "78.9",
        "Temperature": "77.0",
        "Dew Point": "45.6",
        "Relative Humidity": "32.93",
        "Heat Index": "",
        "Wind Speed": "9.0",
        "Wind Gust": "",
        "Wind Direction": "208.67",
        "Wind Chill": "",
        "Precipitation": "0.0",
        "Precipitation Cover": "0.0",
        "Snow Depth": "",
        "Visibility": "6.3",
        "Cloud Cover": "6.0",
        "Sea Level Pressure": "",
        "Weather Type": "",
        "Latitude": "41.9032",
        "Longitude": "12.4957",
        "Resolved Address": "Roma, Lazio, Italia",
        "Name": "Roma, Lazio, Italia",
        "Info": "",
        "Conditions": "Clear"
    },
    "05/14/2009 21:00:00": {
        "Address": "Italy,Rome",
        "Date time": "05/14/2009 21:00:00",
        "Minimum Temperature": "62.7",
        "Maximum Temperature": "69.7",
        "Temperature": "64.5",
        "Dew Point": "47.8",
        "Relative Humidity": "55.26",
        "Heat Index": "",
        "Wind Speed": "4.7",
        "Wind Gust": "",
        "Wind Direction": "88.33",
        "Wind Chill": "",
        "Precipitation": "0.0",
        "Precipitation Cover": "0.0",
        "Snow Depth": "",
        "Visibility": "6.7",
        "Cloud Cover": "42.7",
        "Sea Level Pressure": "",
        "Weather Type": "",
        "Latitude": "41.9032",
        "Longitude": "12.4957",
        "Resolved Address": "Roma, Lazio, Italia",
        "Name": "Roma, Lazio, Italia",
        "Info": "",
        "Conditions": "Partially cloudy"
    },
    "05/15/2009 09:00:00": {
        "Address": "Italy,Rome",
        "Date time": "05/15/2009 09:00:00",
        "Minimum Temperature": "66.7",
        "Maximum Temperature": "74.8",
        "Temperature": "69.9",
        "Dew Point": "55.1",
        "Relative Humidity": "59.74",
        "Heat Index": "",
        "Wind Speed": "6.9",
        "Wind Gust": "",
        "Wind Direction": "151.67",
        "Wind Chill": "",
        "Precipitation": "0.0",
        "Precipitation Cover": "0.0",
        "Snow Depth": "",
        "Visibility": "6.7",
        "Cloud Cover": "44.9",
        "Sea Level Pressure": "",
        "Weather Type": "",
        "Latitude": "41.9032",
        "Longitude": "12.4957",
        "Resolved Address": "Roma, Lazio, Italia",
        "Name": "Roma, Lazio, Italia",
        "Info": "",
        "Conditions": "Partially cloudy"
    },
    "05/15/2009 15:00:00": {
        "Address": "Italy,Rome",
        "Date time": "05/15/2009 15:00:00",
        "Minimum Temperature": "70.1",
        "Maximum Temperature": "73.3",
        "Temperature": "71.7",
        "Dew Point": "54.5",
        "Relative Humidity": "54.74",
        "Heat Index": "",
        "Wind Speed": "12.7",
        "Wind Gust": "",
        "Wind Direction": "203.67",
        "Wind Chill": "",
        "Precipitation": "0.0",
        "Precipitation Cover": "0.0",
        "Snow Depth": "",
        "Visibility": "6.8",
        "Cloud Cover": "60.9",
        "Sea Level Pressure": "",
        "Weather Type": "",
        "Latitude": "41.9032",
        "Longitude": "12.4957",
        "Resolved Address": "Roma, Lazio, Italia",
        "Name": "Roma, Lazio, Italia",
        "Info": "",
        "Conditions": "Partially cloudy"
    },
    "05/15/2009 21:00:00": {
        "Address": "Italy,Rome",
        "Date time": "05/15/2009 21:00:00",
        "Minimum Temperature": "64.5",
        "Maximum Temperature": "68.1",
        "Temperature": "67.2",
        "Dew Point": "57.1",
        "Relative Humidity": "70.25",
        "Heat Index": "",
        "Wind Speed": "11.4",
        "Wind Gust": "",
        "Wind Direction": "136.67",
        "Wind Chill": "",
        "Precipitation": "0.0",
        "Precipitation Cover": "0.0",
        "Snow Depth": "",
        "Visibility": "6.8",
        "Cloud Cover": "50.0",
        "Sea Level Pressure": "",
        "Weather Type": "",
        "Latitude": "41.9032",
        "Longitude": "12.4957",
        "Resolved Address": "Roma, Lazio, Italia",
        "Name": "Roma, Lazio, Italia",
        "Info": "",
        "Conditions": "Partially cloudy"
    },
    "05/16/2009 09:00:00": {
        "Address": "Italy,Rome",
        "Date time": "05/16/2009 09:00:00",
        "Minimum Temperature": "66.5",
        "Maximum Temperature": "86.1",
        "Temperature": "78.5",
        "Dew Point": "56.0",
        "Relative Humidity": "49.18",
        "Heat Index": "83.3",
        "Wind Speed": "12.2",
        "Wind Gust": "",
        "Wind Direction": "190.83",
        "Wind Chill": "",
        "Precipitation": "0.0",
        "Precipitation Cover": "0.0",
        "Snow Depth": "",
        "Visibility": "6.6",
        "Cloud Cover": "32.7",
        "Sea Level Pressure": "",
        "Weather Type": "",
        "Latitude": "41.9032",
        "Longitude": "12.4957",
        "Resolved Address": "Roma, Lazio, Italia",
        "Name": "Roma, Lazio, Italia",
        "Info": "",
        "Conditions": "Partially cloudy"
    },
    "05/16/2009 15:00:00": {
        "Address": "Italy,Rome",
        "Date time": "05/16/2009 15:00:00",
        "Minimum Temperature": "76.6",
        "Maximum Temperature": "85.9",
        "Temperature": "81.9",
        "Dew Point": "52.1",
        "Relative Humidity": "35.86",
        "Heat Index": "83.5",
        "Wind Speed": "15.4",
        "Wind Gust": "",
        "Wind Direction": "170.17",
        "Wind Chill": "",
        "Precipitation": "0.0",
        "Precipitation Cover": "0.0",
        "Snow Depth": "",
        "Visibility": "6.4",
        "Cloud Cover": "8.2",
        "Sea Level Pressure": "",
        "Weather Type": "",
        "Latitude": "41.9032",
        "Longitude": "12.4957",
        "Resolved Address": "Roma, Lazio, Italia",
        "Name": "Roma, Lazio, Italia",
        "Info": "",
        "Conditions": "Clear"
    },
    "05/16/2009 21:00:00": {
        "Address": "Italy,Rome",
        "Date time": "05/16/2009 21:00:00",
        "Minimum Temperature": "66.3",
        "Maximum Temperature": "75.1",
        "Temperature": "69.8",
        "Dew Point": "56.2",
        "Relative Humidity": "63.76",
        "Heat Index": "",
        "Wind Speed": "6.6",
        "Wind Gust": "",
        "Wind Direction": "150.6",
        "Wind Chill": "",
        "Precipitation": "0.0",
        "Precipitation Cover": "0.0",
        "Snow Depth": "",
        "Visibility": "6.7",
        "Cloud Cover": "53.3",
        "Sea Level Pressure": "",
        "Weather Type": "",
        "Latitude": "41.9032",
        "Longitude": "12.4957",
        "Resolved Address": "Roma, Lazio, Italia",
        "Name": "Roma, Lazio, Italia",
        "Info": "",
        "Conditions": "Partially cloudy"
    },
    "05/17/2009 09:00:00": {
        "Address": "Italy,Rome",
        "Date time": "05/17/2009 09:00:00",
        "Minimum Temperature": "70.1",
        "Maximum Temperature": "85.9",
        "Temperature": "79.2",
        "Dew Point": "59.1",
        "Relative Humidity": "51.48",
        "Heat Index": "85.4",
        "Wind Speed": "5.8",
        "Wind Gust": "",
        "Wind Direction": "143.5",
        "Wind Chill": "",
        "Precipitation": "0.0",
        "Precipitation Cover": "0.0",
        "Snow Depth": "",
        "Visibility": "6.3",
        "Cloud Cover": "1.9",
        "Sea Level Pressure": "",
        "Weather Type": "",
        "Latitude": "41.9032",
        "Longitude": "12.4957",
        "Resolved Address": "Roma, Lazio, Italia",
        "Name": "Roma, Lazio, Italia",
        "Info": "",
        "Conditions": "Clear"
    },
    "05/17/2009 15:00:00": {
        "Address": "Italy,Rome",
        "Date time": "05/17/2009 15:00:00",
        "Minimum Temperature": "78.7",
        "Maximum Temperature": "84.5",
        "Temperature": "82.6",
        "Dew Point": "57.8",
        "Relative Humidity": "42.93",
        "Heat Index": "84.2",
        "Wind Speed": "13.4",
        "Wind Gust": "",
        "Wind Direction": "266.0",
        "Wind Chill": "",
        "Precipitation": "0.0",
        "Precipitation Cover": "0.0",
        "Snow Depth": "",
        "Visibility": "6.7",
        "Cloud Cover": "32.3",
        "Sea Level Pressure": "",
        "Weather Type": "",
        "Latitude": "41.9032",
        "Longitude": "12.4957",
        "Resolved Address": "Roma, Lazio, Italia",
        "Name": "Roma, Lazio, Italia",
        "Info": "",
        "Conditions": "Partially cloudy"
    },
    "05/17/2009 21:00:00": {
        "Address": "Italy,Rome",
        "Date time": "05/17/2009 21:00:00",
        "Minimum Temperature": "66.3",
        "Maximum Temperature": "76.4",
        "Temperature": "69.2",
        "Dew Point": "57.9",
        "Relative Humidity": "68.53",
        "Heat Index": "",
        "Wind Speed": "4.7",
        "Wind Gust": "",
        "Wind Direction": "157.5",
        "Wind Chill": "",
        "Precipitation": "0.0",
        "Precipitation Cover": "0.0",
        "Snow Depth": "",
        "Visibility": "6.3",
        "Cloud Cover": "5.4",
        "Sea Level Pressure": "",
        "Weather Type": "",
        "Latitude": "41.9032",
        "Longitude": "12.4957",
        "Resolved Address": "Roma, Lazio, Italia",
        "Name": "Roma, Lazio, Italia",
        "Info": "",
        "Conditions": "Clear"
    },
    "05/18/2009 09:00:00": {
        "Address": "Italy,Rome",
        "Date time": "05/18/2009 09:00:00",
        "Minimum Temperature": "64.9",
        "Maximum Temperature": "84.1",
        "Temperature": "77.1",
        "Dew Point": "58.3",
        "Relative Humidity": "54.65",
        "Heat Index": "83.3",
        "Wind Speed": "9.2",
        "Wind Gust": "",
        "Wind Direction": "264.33",
        "Wind Chill": "",
        "Precipitation": "0.0",
        "Precipitation Cover": "0.0",
        "Snow Depth": "",
        "Visibility": "6.3",
        "Cloud Cover": "5.6",
        "Sea Level Pressure": "",
        "Weather Type": "",
        "Latitude": "41.9032",
        "Longitude": "12.4957",
        "Resolved Address": "Roma, Lazio, Italia",
        "Name": "Roma, Lazio, Italia",
        "Info": "",
        "Conditions": "Clear"
    },
    "05/18/2009 15:00:00": {
        "Address": "Italy,Rome",
        "Date time": "05/18/2009 15:00:00",
        "Minimum Temperature": "75.1",
        "Maximum Temperature": "82.5",
        "Temperature": "79.9",
        "Dew Point": "59.3",
        "Relative Humidity": "49.58",
        "Heat Index": "82.6",
        "Wind Speed": "11.0",
        "Wind Gust": "",
        "Wind Direction": "240.0",
        "Wind Chill": "",
        "Precipitation": "0.0",
        "Precipitation Cover": "0.0",
        "Snow Depth": "",
        "Visibility": "6.3",
        "Cloud Cover": "2.6",
        "Sea Level Pressure": "",
        "Weather Type": "",
        "Latitude": "41.9032",
        "Longitude": "12.4957",
        "Resolved Address": "Roma, Lazio, Italia",
        "Name": "Roma, Lazio, Italia",
        "Info": "",
        "Conditions": "Clear"
    },
    "05/18/2009 21:00:00": {
        "Address": "Italy,Rome",
        "Date time": "05/18/2009 21:00:00",
        "Minimum Temperature": "64.5",
        "Maximum Temperature": "73.0",
        "Temperature": "67.4",
        "Dew Point": "62.2",
        "Relative Humidity": "84.25",
        "Heat Index": "",
        "Wind Speed": "3.4",
        "Wind Gust": "",
        "Wind Direction": "182.75",
        "Wind Chill": "",
        "Precipitation": "0.0",
        "Precipitation Cover": "0.0",
        "Snow Depth": "",
        "Visibility": "6.2",
        "Cloud Cover": "0.0",
        "Sea Level Pressure": "",
        "Weather Type": "",
        "Latitude": "41.9032",
        "Longitude": "12.4957",
        "Resolved Address": "Roma, Lazio, Italia",
        "Name": "Roma, Lazio, Italia",
        "Info": "",
        "Conditions": "Clear"
    },
    "05/19/2009 09:00:00": {
        "Address": "Italy,Rome",
        "Date time": "05/19/2009 09:00:00",
        "Minimum Temperature": "71.7",
        "Maximum Temperature": "86.1",
        "Temperature": "79.9",
        "Dew Point": "58.2",
        "Relative Humidity": "49.04",
        "Heat Index": "83.9",
        "Wind Speed": "8.3",
        "Wind Gust": "",
        "Wind Direction": "330.67",
        "Wind Chill": "",
        "Precipitation": "0.0",
        "Precipitation Cover": "0.0",
        "Snow Depth": "",
        "Visibility": "6.3",
        "Cloud Cover": "2.6",
        "Sea Level Pressure": "",
        "Weather Type": "",
        "Latitude": "41.9032",
        "Longitude": "12.4957",
        "Resolved Address": "Roma, Lazio, Italia",
        "Name": "Roma, Lazio, Italia",
        "Info": "",
        "Conditions": "Clear"
    },
    "05/19/2009 15:00:00": {
        "Address": "Italy,Rome",
        "Date time": "05/19/2009 15:00:00",
        "Minimum Temperature": "80.2",
        "Maximum Temperature": "87.4",
        "Temperature": "83.4",
        "Dew Point": "55.6",
        "Relative Humidity": "38.77",
        "Heat Index": "85.8",
        "Wind Speed": "11.4",
        "Wind Gust": "",
        "Wind Direction": "251.83",
        "Wind Chill": "",
        "Precipitation": "0.0",
        "Precipitation Cover": "0.0",
        "Snow Depth": "",
        "Visibility": "6.3",
        "Cloud Cover": "3.8",
        "Sea Level Pressure": "",
        "Weather Type": "",
        "Latitude": "41.9032",
        "Longitude": "12.4957",
        "Resolved Address": "Roma, Lazio, Italia",
        "Name": "Roma, Lazio, Italia",
        "Info": "",
        "Conditions": "Clear"
    },
    "05/19/2009 21:00:00": {
        "Address": "Italy,Rome",
        "Date time": "05/19/2009 21:00:00",
        "Minimum Temperature": "64.5",
        "Maximum Temperature": "75.3",
        "Temperature": "69.6",
        "Dew Point": "53.1",
        "Relative Humidity": "56.47",
        "Heat Index": "",
        "Wind Speed": "3.4",
        "Wind Gust": "",
        "Wind Direction": "206.67",
        "Wind Chill": "",
        "Precipitation": "0.0",
        "Precipitation Cover": "0.0",
        "Snow Depth": "",
        "Visibility": "6.2",
        "Cloud Cover": "0.0",
        "Sea Level Pressure": "",
        "Weather Type": "",
        "Latitude": "41.9032",
        "Longitude": "12.4957",
        "Resolved Address": "Roma, Lazio, Italia",
        "Name": "Roma, Lazio, Italia",
        "Info": "",
        "Conditions": "Clear"
    },
    "05/20/2009 09:00:00": {
        "Address": "Italy,Rome",
        "Date time": "05/20/2009 09:00:00",
        "Minimum Temperature": "70.3",
        "Maximum Temperature": "86.1",
        "Temperature": "80.2",
        "Dew Point": "56.6",
        "Relative Humidity": "45.75",
        "Heat Index": "84.5",
        "Wind Speed": "8.1",
        "Wind Gust": "",
        "Wind Direction": "306.0",
        "Wind Chill": "",
        "Precipitation": "0.0",
        "Precipitation Cover": "0.0",
        "Snow Depth": "",
        "Visibility": "6.3",
        "Cloud Cover": "2.6",
        "Sea Level Pressure": "",
        "Weather Type": "",
        "Latitude": "41.9032",
        "Longitude": "12.4957",
        "Resolved Address": "Roma, Lazio, Italia",
        "Name": "Roma, Lazio, Italia",
        "Info": "",
        "Conditions": "Clear"
    },
    "05/20/2009 15:00:00": {
        "Address": "Italy,Rome",
        "Date time": "05/20/2009 15:00:00",
        "Minimum Temperature": "78.7",
        "Maximum Temperature": "86.1",
        "Temperature": "83.9",
        "Dew Point": "55.8",
        "Relative Humidity": "38.57",
        "Heat Index": "84.5",
        "Wind Speed": "14.0",
        "Wind Gust": "",
        "Wind Direction": "280.5",
        "Wind Chill": "",
        "Precipitation": "0.0",
        "Precipitation Cover": "0.0",
        "Snow Depth": "",
        "Visibility": "6.5",
        "Cloud Cover": "15.6",
        "Sea Level Pressure": "",
        "Weather Type": "",
        "Latitude": "41.9032",
        "Longitude": "12.4957",
        "Resolved Address": "Roma, Lazio, Italia",
        "Name": "Roma, Lazio, Italia",
        "Info": "",
        "Conditions": "Clear"
    },
    "05/20/2009 21:00:00": {
        "Address": "Italy,Rome",
        "Date time": "05/20/2009 21:00:00",
        "Minimum Temperature": "66.3",
        "Maximum Temperature": "75.3",
        "Temperature": "69.6",
        "Dew Point": "55.2",
        "Relative Humidity": "60.72",
        "Heat Index": "",
        "Wind Speed": "6.8",
        "Wind Gust": "",
        "Wind Direction": "177.0",
        "Wind Chill": "",
        "Precipitation": "0.0",
        "Precipitation Cover": "0.0",
        "Snow Depth": "",
        "Visibility": "6.3",
        "Cloud Cover": "5.0",
        "Sea Level Pressure": "",
        "Weather Type": "",
        "Latitude": "41.9032",
        "Longitude": "12.4957",
        "Resolved Address": "Roma, Lazio, Italia",
        "Name": "Roma, Lazio, Italia",
        "Info": "",
        "Conditions": "Clear"
    },
    "05/21/2009 09:00:00": {
        "Address": "Italy,Rome",
        "Date time": "05/21/2009 09:00:00",
        "Minimum Temperature": "72.1",
        "Maximum Temperature": "86.1",
        "Temperature": "80.0",
        "Dew Point": "57.2",
        "Relative Humidity": "47.02",
        "Heat Index": "84.5",
        "Wind Speed": "8.9",
        "Wind Gust": "",
        "Wind Direction": "138.0",
        "Wind Chill": "",
        "Precipitation": "0.0",
        "Precipitation Cover": "0.0",
        "Snow Depth": "",
        "Visibility": "6.2",
        "Cloud Cover": "1.3",
        "Sea Level Pressure": "",
        "Weather Type": "",
        "Latitude": "41.9032",
        "Longitude": "12.4957",
        "Resolved Address": "Roma, Lazio, Italia",
        "Name": "Roma, Lazio, Italia",
        "Info": "",
        "Conditions": "Clear"
    },
    "05/21/2009 15:00:00": {
        "Address": "Italy,Rome",
        "Date time": "05/21/2009 15:00:00",
        "Minimum Temperature": "77.1",
        "Maximum Temperature": "87.4",
        "Temperature": "82.6",
        "Dew Point": "56.9",
        "Relative Humidity": "41.85",
        "Heat Index": "85.7",
        "Wind Speed": "13.1",
        "Wind Gust": "",
        "Wind Direction": "217.67",
        "Wind Chill": "",
        "Precipitation": "0.0",
        "Precipitation Cover": "0.0",
        "Snow Depth": "",
        "Visibility": "6.2",
        "Cloud Cover": "0.6",
        "Sea Level Pressure": "",
        "Weather Type": "",
        "Latitude": "41.9032",
        "Longitude": "12.4957",
        "Resolved Address": "Roma, Lazio, Italia",
        "Name": "Roma, Lazio, Italia",
        "Info": "",
        "Conditions": "Clear"
    },
    "05/21/2009 21:00:00": {
        "Address": "Italy,Rome",
        "Date time": "05/21/2009 21:00:00",
        "Minimum Temperature": "68.1",
        "Maximum Temperature": "75.3",
        "Temperature": "71.4",
        "Dew Point": "58.3",
        "Relative Humidity": "63.49",
        "Heat Index": "",
        "Wind Speed": "3.4",
        "Wind Gust": "",
        "Wind Direction": "157.83",
        "Wind Chill": "",
        "Precipitation": "0.0",
        "Precipitation Cover": "0.0",
        "Snow Depth": "",
        "Visibility": "6.2",
        "Cloud Cover": "0.0",
        "Sea Level Pressure": "",
        "Weather Type": "",
        "Latitude": "41.9032",
        "Longitude": "12.4957",
        "Resolved Address": "Roma, Lazio, Italia",
        "Name": "Roma, Lazio, Italia",
        "Info": "",
        "Conditions": "Clear"
    },
    "05/22/2009 09:00:00": {
        "Address": "Italy,Rome",
        "Date time": "05/22/2009 09:00:00",
        "Minimum Temperature": "70.3",
        "Maximum Temperature": "85.9",
        "Temperature": "80.0",
        "Dew Point": "61.2",
        "Relative Humidity": "54.02",
        "Heat Index": "85.6",
        "Wind Speed": "6.7",
        "Wind Gust": "",
        "Wind Direction": "206.0",
        "Wind Chill": "",
        "Precipitation": "0.0",
        "Precipitation Cover": "0.0",
        "Snow Depth": "",
        "Visibility": "6.2",
        "Cloud Cover": "0.0",
        "Sea Level Pressure": "",
        "Weather Type": "",
        "Latitude": "41.9032",
        "Longitude": "12.4957",
        "Resolved Address": "Roma, Lazio, Italia",
        "Name": "Roma, Lazio, Italia",
        "Info": "",
        "Conditions": "Clear"
    },
    "05/22/2009 15:00:00": {
        "Address": "Italy,Rome",
        "Date time": "05/22/2009 15:00:00",
        "Minimum Temperature": "76.6",
        "Maximum Temperature": "84.3",
        "Temperature": "81.5",
        "Dew Point": "57.6",
        "Relative Humidity": "44.4",
        "Heat Index": "84.0",
        "Wind Speed": "10.3",
        "Wind Gust": "",
        "Wind Direction": "228.67",
        "Wind Chill": "",
        "Precipitation": "0.0",
        "Precipitation Cover": "0.0",
        "Snow Depth": "",
        "Visibility": "6.2",
        "Cloud Cover": "3.0",
        "Sea Level Pressure": "",
        "Weather Type": "",
        "Latitude": "41.9032",
        "Longitude": "12.4957",
        "Resolved Address": "Roma, Lazio, Italia",
        "Name": "Roma, Lazio, Italia",
        "Info": "",
        "Conditions": "Clear"
    },
    "05/22/2009 21:00:00": {
        "Address": "Italy,Rome",
        "Date time": "05/22/2009 21:00:00",
        "Minimum Temperature": "64.5",
        "Maximum Temperature": "74.8",
        "Temperature": "68.0",
        "Dew Point": "59.1",
        "Relative Humidity": "74.11",
        "Heat Index": "",
        "Wind Speed": "5.0",
        "Wind Gust": "",
        "Wind Direction": "152.5",
        "Wind Chill": "",
        "Precipitation": "0.0",
        "Precipitation Cover": "0.0",
        "Snow Depth": "",
        "Visibility": "6.2",
        "Cloud Cover": "1.1",
        "Sea Level Pressure": "",
        "Weather Type": "",
        "Latitude": "41.9032",
        "Longitude": "12.4957",
        "Resolved Address": "Roma, Lazio, Italia",
        "Name": "Roma, Lazio, Italia",
        "Info": "",
        "Conditions": "Clear"
    },
    "05/23/2009 09:00:00": {
        "Address": "Italy,Rome",
        "Date time": "05/23/2009 09:00:00",
        "Minimum Temperature": "68.5",
        "Maximum Temperature": "86.1",
        "Temperature": "79.5",
        "Dew Point": "59.9",
        "Relative Humidity": "53.11",
        "Heat Index": "85.4",
        "Wind Speed": "8.1",
        "Wind Gust": "",
        "Wind Direction": "206.17",
        "Wind Chill": "",
        "Precipitation": "0.0",
        "Precipitation Cover": "0.0",
        "Snow Depth": "",
        "Visibility": "6.2",
        "Cloud Cover": "0.0",
        "Sea Level Pressure": "",
        "Weather Type": "",
        "Latitude": "41.9032",
        "Longitude": "12.4957",
        "Resolved Address": "Roma, Lazio, Italia",
        "Name": "Roma, Lazio, Italia",
        "Info": "",
        "Conditions": "Clear"
    },
    "05/23/2009 15:00:00": {
        "Address": "Italy,Rome",
        "Date time": "05/23/2009 15:00:00",
        "Minimum Temperature": "78.7",
        "Maximum Temperature": "84.5",
        "Temperature": "83.1",
        "Dew Point": "52.0",
        "Relative Humidity": "34.34",
        "Heat Index": "82.8",
        "Wind Speed": "11.4",
        "Wind Gust": "",
        "Wind Direction": "226.83",
        "Wind Chill": "",
        "Precipitation": "0.0",
        "Precipitation Cover": "0.0",
        "Snow Depth": "",
        "Visibility": "6.2",
        "Cloud Cover": "0.0",
        "Sea Level Pressure": "",
        "Weather Type": "",
        "Latitude": "41.9032",
        "Longitude": "12.4957",
        "Resolved Address": "Roma, Lazio, Italia",
        "Name": "Roma, Lazio, Italia",
        "Info": "",
        "Conditions": "Clear"
    },
    "05/23/2009 21:00:00": {
        "Address": "Italy,Rome",
        "Date time": "05/23/2009 21:00:00",
        "Minimum Temperature": "66.3",
        "Maximum Temperature": "71.9",
        "Temperature": "69.0",
        "Dew Point": "54.3",
        "Relative Humidity": "59.68",
        "Heat Index": "",
        "Wind Speed": "5.4",
        "Wind Gust": "",
        "Wind Direction": "142.8",
        "Wind Chill": "",
        "Precipitation": "0.0",
        "Precipitation Cover": "0.0",
        "Snow Depth": "",
        "Visibility": "6.2",
        "Cloud Cover": "0.0",
        "Sea Level Pressure": "",
        "Weather Type": "",
        "Latitude": "41.9032",
        "Longitude": "12.4957",
        "Resolved Address": "Roma, Lazio, Italia",
        "Name": "Roma, Lazio, Italia",
        "Info": "",
        "Conditions": "Clear"
    },
    "05/24/2009 09:00:00": {
        "Address": "Italy,Rome",
        "Date time": "05/24/2009 09:00:00",
        "Minimum Temperature": "69.0",
        "Maximum Temperature": "87.9",
        "Temperature": "80.5",
        "Dew Point": "58.0",
        "Relative Humidity": "47.91",
        "Heat Index": "87.8",
        "Wind Speed": "4.8",
        "Wind Gust": "",
        "Wind Direction": "252.0",
        "Wind Chill": "",
        "Precipitation": "0.0",
        "Precipitation Cover": "0.0",
        "Snow Depth": "",
        "Visibility": "6.2",
        "Cloud Cover": "0.0",
        "Sea Level Pressure": "",
        "Weather Type": "",
        "Latitude": "41.9032",
        "Longitude": "12.4957",
        "Resolved Address": "Roma, Lazio, Italia",
        "Name": "Roma, Lazio, Italia",
        "Info": "",
        "Conditions": "Clear"
    },
    "05/24/2009 15:00:00": {
        "Address": "Italy,Rome",
        "Date time": "05/24/2009 15:00:00",
        "Minimum Temperature": "78.7",
        "Maximum Temperature": "87.9",
        "Temperature": "84.3",
        "Dew Point": "57.9",
        "Relative Humidity": "40.87",
        "Heat Index": "87.3",
        "Wind Speed": "10.8",
        "Wind Gust": "",
        "Wind Direction": "245.83",
        "Wind Chill": "",
        "Precipitation": "0.0",
        "Precipitation Cover": "0.0",
        "Snow Depth": "",
        "Visibility": "6.2",
        "Cloud Cover": "0.0",
        "Sea Level Pressure": "",
        "Weather Type": "",
        "Latitude": "41.9032",
        "Longitude": "12.4957",
        "Resolved Address": "Roma, Lazio, Italia",
        "Name": "Roma, Lazio, Italia",
        "Info": "",
        "Conditions": "Clear"
    },
    "05/24/2009 21:00:00": {
        "Address": "Italy,Rome",
        "Date time": "05/24/2009 21:00:00",
        "Minimum Temperature": "66.3",
        "Maximum Temperature": "75.3",
        "Temperature": "70.2",
        "Dew Point": "61.0",
        "Relative Humidity": "73.13",
        "Heat Index": "",
        "Wind Speed": "2.6",
        "Wind Gust": "",
        "Wind Direction": "165.0",
        "Wind Chill": "",
        "Precipitation": "0.0",
        "Precipitation Cover": "0.0",
        "Snow Depth": "",
        "Visibility": "6.2",
        "Cloud Cover": "0.0",
        "Sea Level Pressure": "",
        "Weather Type": "",
        "Latitude": "41.9032",
        "Longitude": "12.4957",
        "Resolved Address": "Roma, Lazio, Italia",
        "Name": "Roma, Lazio, Italia",
        "Info": "",
        "Conditions": "Clear"
    },
    "05/25/2009 09:00:00": {
        "Address": "Italy,Rome",
        "Date time": "05/25/2009 09:00:00",
        "Minimum Temperature": "70.6",
        "Maximum Temperature": "89.7",
        "Temperature": "81.7",
        "Dew Point": "63.8",
        "Relative Humidity": "55.56",
        "Heat Index": "91.9",
        "Wind Speed": "7.1",
        "Wind Gust": "",
        "Wind Direction": "284.17",
        "Wind Chill": "",
        "Precipitation": "0.0",
        "Precipitation Cover": "0.0",
        "Snow Depth": "",
        "Visibility": "6.2",
        "Cloud Cover": "0.6",
        "Sea Level Pressure": "",
        "Weather Type": "",
        "Latitude": "41.9032",
        "Longitude": "12.4957",
        "Resolved Address": "Roma, Lazio, Italia",
        "Name": "Roma, Lazio, Italia",
        "Info": "",
        "Conditions": "Clear"
    },
    "05/25/2009 15:00:00": {
        "Address": "Italy,Rome",
        "Date time": "05/25/2009 15:00:00",
        "Minimum Temperature": "80.5",
        "Maximum Temperature": "88.1",
        "Temperature": "85.3",
        "Dew Point": "58.2",
        "Relative Humidity": "40.12",
        "Heat Index": "89.3",
        "Wind Speed": "10.0",
        "Wind Gust": "",
        "Wind Direction": "226.83",
        "Wind Chill": "",
        "Precipitation": "0.0",
        "Precipitation Cover": "0.0",
        "Snow Depth": "",
        "Visibility": "6.3",
        "Cloud Cover": "4.0",
        "Sea Level Pressure": "",
        "Weather Type": "",
        "Latitude": "41.9032",
        "Longitude": "12.4957",
        "Resolved Address": "Roma, Lazio, Italia",
        "Name": "Roma, Lazio, Italia",
        "Info": "",
        "Conditions": "Clear"
    },
    "05/25/2009 21:00:00": {
        "Address": "Italy,Rome",
        "Date time": "05/25/2009 21:00:00",
        "Minimum Temperature": "69.9",
        "Maximum Temperature": "77.1",
        "Temperature": "72.9",
        "Dew Point": "58.3",
        "Relative Humidity": "60.79",
        "Heat Index": "",
        "Wind Speed": "5.7",
        "Wind Gust": "",
        "Wind Direction": "196.33",
        "Wind Chill": "",
        "Precipitation": "0.0",
        "Precipitation Cover": "0.0",
        "Snow Depth": "",
        "Visibility": "6.2",
        "Cloud Cover": "0.0",
        "Sea Level Pressure": "",
        "Weather Type": "",
        "Latitude": "41.9032",
        "Longitude": "12.4957",
        "Resolved Address": "Roma, Lazio, Italia",
        "Name": "Roma, Lazio, Italia",
        "Info": "",
        "Conditions": "Clear"
    },
    "05/26/2009 09:00:00": {
        "Address": "Italy,Rome",
        "Date time": "05/26/2009 09:00:00",
        "Minimum Temperature": "72.4",
        "Maximum Temperature": "86.5",
        "Temperature": "82.0",
        "Dew Point": "60.1",
        "Relative Humidity": "48.92",
        "Heat Index": "85.4",
        "Wind Speed": "6.8",
        "Wind Gust": "",
        "Wind Direction": "218.17",
        "Wind Chill": "",
        "Precipitation": "0.0",
        "Precipitation Cover": "0.0",
        "Snow Depth": "",
        "Visibility": "6.2",
        "Cloud Cover": "1.3",
        "Sea Level Pressure": "",
        "Weather Type": "",
        "Latitude": "41.9032",
        "Longitude": "12.4957",
        "Resolved Address": "Roma, Lazio, Italia",
        "Name": "Roma, Lazio, Italia",
        "Info": "",
        "Conditions": "Clear"
    },
    "05/26/2009 15:00:00": {
        "Address": "Italy,Rome",
        "Date time": "05/26/2009 15:00:00",
        "Minimum Temperature": "80.7",
        "Maximum Temperature": "89.7",
        "Temperature": "85.6",
        "Dew Point": "53.1",
        "Relative Humidity": "33.26",
        "Heat Index": "87.1",
        "Wind Speed": "10.7",
        "Wind Gust": "",
        "Wind Direction": "245.5",
        "Wind Chill": "",
        "Precipitation": "0.0",
        "Precipitation Cover": "0.0",
        "Snow Depth": "",
        "Visibility": "6.4",
        "Cloud Cover": "7.6",
        "Sea Level Pressure": "",
        "Weather Type": "",
        "Latitude": "41.9032",
        "Longitude": "12.4957",
        "Resolved Address": "Roma, Lazio, Italia",
        "Name": "Roma, Lazio, Italia",
        "Info": "",
        "Conditions": "Clear"
    },
    "05/26/2009 21:00:00": {
        "Address": "Italy,Rome",
        "Date time": "05/26/2009 21:00:00",
        "Minimum Temperature": "69.9",
        "Maximum Temperature": "77.1",
        "Temperature": "72.6",
        "Dew Point": "58.5",
        "Relative Humidity": "62.11",
        "Heat Index": "",
        "Wind Speed": "6.9",
        "Wind Gust": "",
        "Wind Direction": "153.5",
        "Wind Chill": "",
        "Precipitation": "0.0",
        "Precipitation Cover": "0.0",
        "Snow Depth": "",
        "Visibility": "6.2",
        "Cloud Cover": "0.0",
        "Sea Level Pressure": "",
        "Weather Type": "",
        "Latitude": "41.9032",
        "Longitude": "12.4957",
        "Resolved Address": "Roma, Lazio, Italia",
        "Name": "Roma, Lazio, Italia",
        "Info": "",
        "Conditions": "Clear"
    },
    "05/27/2009 09:00:00": {
        "Address": "Italy,Rome",
        "Date time": "05/27/2009 09:00:00",
        "Minimum Temperature": "71.9",
        "Maximum Temperature": "79.1",
        "Temperature": "76.3",
        "Dew Point": "64.5",
        "Relative Humidity": "67.05",
        "Heat Index": "",
        "Wind Speed": "12.4",
        "Wind Gust": "",
        "Wind Direction": "196.0",
        "Wind Chill": "",
        "Precipitation": "0.0",
        "Precipitation Cover": "0.0",
        "Snow Depth": "",
        "Visibility": "6.8",
        "Cloud Cover": "55.8",
        "Sea Level Pressure": "",
        "Weather Type": "",
        "Latitude": "41.9032",
        "Longitude": "12.4957",
        "Resolved Address": "Roma, Lazio, Italia",
        "Name": "Roma, Lazio, Italia",
        "Info": "",
        "Conditions": "Partially cloudy"
    },
    "05/27/2009 15:00:00": {
        "Address": "Italy,Rome",
        "Date time": "05/27/2009 15:00:00",
        "Minimum Temperature": "73.3",
        "Maximum Temperature": "78.9",
        "Temperature": "76.6",
        "Dew Point": "65.1",
        "Relative Humidity": "67.74",
        "Heat Index": "",
        "Wind Speed": "12.6",
        "Wind Gust": "",
        "Wind Direction": "220.83",
        "Wind Chill": "",
        "Precipitation": "0.0",
        "Precipitation Cover": "0.0",
        "Snow Depth": "",
        "Visibility": "6.8",
        "Cloud Cover": "50.0",
        "Sea Level Pressure": "",
        "Weather Type": "",
        "Latitude": "41.9032",
        "Longitude": "12.4957",
        "Resolved Address": "Roma, Lazio, Italia",
        "Name": "Roma, Lazio, Italia",
        "Info": "",
        "Conditions": "Partially cloudy"
    },
    "05/27/2009 21:00:00": {
        "Address": "Italy,Rome",
        "Date time": "05/27/2009 21:00:00",
        "Minimum Temperature": "66.3",
        "Maximum Temperature": "73.0",
        "Temperature": "69.2",
        "Dew Point": "65.7",
        "Relative Humidity": "88.95",
        "Heat Index": "",
        "Wind Speed": "4.7",
        "Wind Gust": "",
        "Wind Direction": "174.2",
        "Wind Chill": "",
        "Precipitation": "0.0",
        "Precipitation Cover": "0.0",
        "Snow Depth": "",
        "Visibility": "5.1",
        "Cloud Cover": "36.7",
        "Sea Level Pressure": "",
        "Weather Type": "",
        "Latitude": "41.9032",
        "Longitude": "12.4957",
        "Resolved Address": "Roma, Lazio, Italia",
        "Name": "Roma, Lazio, Italia",
        "Info": "",
        "Conditions": "Partially cloudy"
    },
    "05/28/2009 09:00:00": {
        "Address": "Italy,Rome",
        "Date time": "05/28/2009 09:00:00",
        "Minimum Temperature": "69.9",
        "Maximum Temperature": "77.3",
        "Temperature": "73.8",
        "Dew Point": "61.6",
        "Relative Humidity": "65.89",
        "Heat Index": "",
        "Wind Speed": "8.4",
        "Wind Gust": "",
        "Wind Direction": "201.0",
        "Wind Chill": "",
        "Precipitation": "0.0",
        "Precipitation Cover": "0.0",
        "Snow Depth": "",
        "Visibility": "6.6",
        "Cloud Cover": "32.1",
        "Sea Level Pressure": "",
        "Weather Type": "",
        "Latitude": "41.9032",
        "Longitude": "12.4957",
        "Resolved Address": "Roma, Lazio, Italia",
        "Name": "Roma, Lazio, Italia",
        "Info": "",
        "Conditions": "Partially cloudy"
    },
    "05/28/2009 15:00:00": {
        "Address": "Italy,Rome",
        "Date time": "05/28/2009 15:00:00",
        "Minimum Temperature": "73.0",
        "Maximum Temperature": "78.4",
        "Temperature": "76.2",
        "Dew Point": "62.5",
        "Relative Humidity": "62.72",
        "Heat Index": "",
        "Wind Speed": "7.2",
        "Wind Gust": "",
        "Wind Direction": "184.17",
        "Wind Chill": "",
        "Precipitation": "0.0",
        "Precipitation Cover": "0.0",
        "Snow Depth": "",
        "Visibility": "6.8",
        "Cloud Cover": "42.9",
        "Sea Level Pressure": "",
        "Weather Type": "",
        "Latitude": "41.9032",
        "Longitude": "12.4957",
        "Resolved Address": "Roma, Lazio, Italia",
        "Name": "Roma, Lazio, Italia",
        "Info": "",
        "Conditions": "Partially cloudy"
    },
    "05/28/2009 21:00:00": {
        "Address": "Italy,Rome",
        "Date time": "05/28/2009 21:00:00",
        "Minimum Temperature": "62.7",
        "Maximum Temperature": "73.3",
        "Temperature": "67.8",
        "Dew Point": "50.7",
        "Relative Humidity": "54.66",
        "Heat Index": "",
        "Wind Speed": "7.8",
        "Wind Gust": "",
        "Wind Direction": "195.5",
        "Wind Chill": "",
        "Precipitation": "0.0",
        "Precipitation Cover": "0.0",
        "Snow Depth": "",
        "Visibility": "6.3",
        "Cloud Cover": "5.0",
        "Sea Level Pressure": "",
        "Weather Type": "",
        "Latitude": "41.9032",
        "Longitude": "12.4957",
        "Resolved Address": "Roma, Lazio, Italia",
        "Name": "Roma, Lazio, Italia",
        "Info": "",
        "Conditions": "Clear"
    },
    "05/29/2009 09:00:00": {
        "Address": "Italy,Rome",
        "Date time": "05/29/2009 09:00:00",
        "Minimum Temperature": "66.7",
        "Maximum Temperature": "80.2",
        "Temperature": "74.2",
        "Dew Point": "58.0",
        "Relative Humidity": "57.08",
        "Heat Index": "81.5",
        "Wind Speed": "11.4",
        "Wind Gust": "",
        "Wind Direction": "248.5",
        "Wind Chill": "",
        "Precipitation": "0.0",
        "Precipitation Cover": "0.0",
        "Snow Depth": "",
        "Visibility": "6.8",
        "Cloud Cover": "55.8",
        "Sea Level Pressure": "",
        "Weather Type": "",
        "Latitude": "41.9032",
        "Longitude": "12.4957",
        "Resolved Address": "Roma, Lazio, Italia",
        "Name": "Roma, Lazio, Italia",
        "Info": "",
        "Conditions": "Partially cloudy"
    },
    "05/29/2009 15:00:00": {
        "Address": "Italy,Rome",
        "Date time": "05/29/2009 15:00:00",
        "Minimum Temperature": "71.7",
        "Maximum Temperature": "77.3",
        "Temperature": "75.7",
        "Dew Point": "61.3",
        "Relative Humidity": "61.25",
        "Heat Index": "",
        "Wind Speed": "11.1",
        "Wind Gust": "",
        "Wind Direction": "227.33",
        "Wind Chill": "",
        "Precipitation": "0.0",
        "Precipitation Cover": "0.0",
        "Snow Depth": "",
        "Visibility": "6.8",
        "Cloud Cover": "43.3",
        "Sea Level Pressure": "",
        "Weather Type": "",
        "Latitude": "41.9032",
        "Longitude": "12.4957",
        "Resolved Address": "Roma, Lazio, Italia",
        "Name": "Roma, Lazio, Italia",
        "Info": "",
        "Conditions": "Partially cloudy"
    },
    "05/29/2009 21:00:00": {
        "Address": "Italy,Rome",
        "Date time": "05/29/2009 21:00:00",
        "Minimum Temperature": "64.5",
        "Maximum Temperature": "71.5",
        "Temperature": "67.8",
        "Dew Point": "63.1",
        "Relative Humidity": "85.64",
        "Heat Index": "",
        "Wind Speed": "10.3",
        "Wind Gust": "",
        "Wind Direction": "278.75",
        "Wind Chill": "",
        "Precipitation": "0.0",
        "Precipitation Cover": "0.0",
        "Snow Depth": "",
        "Visibility": "6.6",
        "Cloud Cover": "42.9",
        "Sea Level Pressure": "",
        "Weather Type": "",
        "Latitude": "41.9032",
        "Longitude": "12.4957",
        "Resolved Address": "Roma, Lazio, Italia",
        "Name": "Roma, Lazio, Italia",
        "Info": "",
        "Conditions": "Partially cloudy"
    },
    "05/30/2009 09:00:00": {
        "Address": "Italy,Rome",
        "Date time": "05/30/2009 09:00:00",
        "Minimum Temperature": "62.7",
        "Maximum Temperature": "73.7",
        "Temperature": "68.8",
        "Dew Point": "52.1",
        "Relative Humidity": "55.24",
        "Heat Index": "",
        "Wind Speed": "7.8",
        "Wind Gust": "",
        "Wind Direction": "143.33",
        "Wind Chill": "",
        "Precipitation": "0.0",
        "Precipitation Cover": "0.0",
        "Snow Depth": "",
        "Visibility": "6.7",
        "Cloud Cover": "54.0",
        "Sea Level Pressure": "",
        "Weather Type": "",
        "Latitude": "41.9032",
        "Longitude": "12.4957",
        "Resolved Address": "Roma, Lazio, Italia",
        "Name": "Roma, Lazio, Italia",
        "Info": "",
        "Conditions": "Partially cloudy"
    },
    "05/30/2009 15:00:00": {
        "Address": "Italy,Rome",
        "Date time": "05/30/2009 15:00:00",
        "Minimum Temperature": "71.9",
        "Maximum Temperature": "76.9",
        "Temperature": "74.7",
        "Dew Point": "56.1",
        "Relative Humidity": "52.37",
        "Heat Index": "",
        "Wind Speed": "7.9",
        "Wind Gust": "",
        "Wind Direction": "230.67",
        "Wind Chill": "",
        "Precipitation": "0.0",
        "Precipitation Cover": "0.0",
        "Snow Depth": "",
        "Visibility": "6.6",
        "Cloud Cover": "20.2",
        "Sea Level Pressure": "",
        "Weather Type": "",
        "Latitude": "41.9032",
        "Longitude": "12.4957",
        "Resolved Address": "Roma, Lazio, Italia",
        "Name": "Roma, Lazio, Italia",
        "Info": "",
        "Conditions": "Clear"
    },
    "05/30/2009 21:00:00": {
        "Address": "Italy,Rome",
        "Date time": "05/30/2009 21:00:00",
        "Minimum Temperature": "62.7",
        "Maximum Temperature": "68.1",
        "Temperature": "65.4",
        "Dew Point": "54.6",
        "Relative Humidity": "68.51",
        "Heat Index": "",
        "Wind Speed": "4.7",
        "Wind Gust": "",
        "Wind Direction": "168.75",
        "Wind Chill": "",
        "Precipitation": "0.0",
        "Precipitation Cover": "0.0",
        "Snow Depth": "",
        "Visibility": "6.8",
        "Cloud Cover": "33.8",
        "Sea Level Pressure": "",
        "Weather Type": "",
        "Latitude": "41.9032",
        "Longitude": "12.4957",
        "Resolved Address": "Roma, Lazio, Italia",
        "Name": "Roma, Lazio, Italia",
        "Info": "",
        "Conditions": "Partially cloudy"
    },
    "05/31/2009 09:00:00": {
        "Address": "Italy,Rome",
        "Date time": "05/31/2009 09:00:00",
        "Minimum Temperature": "71.7",
        "Maximum Temperature": "76.6",
        "Temperature": "74.5",
        "Dew Point": "61.4",
        "Relative Humidity": "63.67",
        "Heat Index": "",
        "Wind Speed": "14.2",
        "Wind Gust": "",
        "Wind Direction": "166.83",
        "Wind Chill": "",
        "Precipitation": "0.0",
        "Precipitation Cover": "0.0",
        "Snow Depth": "",
        "Visibility": "6.8",
        "Cloud Cover": "85.7",
        "Sea Level Pressure": "",
        "Weather Type": "",
        "Latitude": "41.9032",
        "Longitude": "12.4957",
        "Resolved Address": "Roma, Lazio, Italia",
        "Name": "Roma, Lazio, Italia",
        "Info": "",
        "Conditions": "Overcast"
    },
    "05/31/2009 15:00:00": {
        "Address": "Italy,Rome",
        "Date time": "05/31/2009 15:00:00",
        "Minimum Temperature": "67.9",
        "Maximum Temperature": "75.1",
        "Temperature": "72.0",
        "Dew Point": "61.3",
        "Relative Humidity": "69.07",
        "Heat Index": "",
        "Wind Speed": "16.1",
        "Wind Gust": "",
        "Wind Direction": "180.17",
        "Wind Chill": "",
        "Precipitation": "0.0",
        "Precipitation Cover": "0.0",
        "Snow Depth": "",
        "Visibility": "6.7",
        "Cloud Cover": "74.5",
        "Sea Level Pressure": "",
        "Weather Type": "",
        "Latitude": "41.9032",
        "Longitude": "12.4957",
        "Resolved Address": "Roma, Lazio, Italia",
        "Name": "Roma, Lazio, Italia",
        "Info": "",
        "Conditions": "Partially cloudy"
    },
    "05/31/2009 21:00:00": {
        "Address": "Italy,Rome",
        "Date time": "05/31/2009 21:00:00",
        "Minimum Temperature": "64.5",
        "Maximum Temperature": "67.9",
        "Temperature": "66.0",
        "Dew Point": "59.7",
        "Relative Humidity": "80.42",
        "Heat Index": "",
        "Wind Speed": "11.0",
        "Wind Gust": "",
        "Wind Direction": "122.5",
        "Wind Chill": "",
        "Precipitation": "0.0",
        "Precipitation Cover": "0.0",
        "Snow Depth": "",
        "Visibility": "6.8",
        "Cloud Cover": "50.0",
        "Sea Level Pressure": "",
        "Weather Type": "",
        "Latitude": "41.9032",
        "Longitude": "12.4957",
        "Resolved Address": "Roma, Lazio, Italia",
        "Name": "Roma, Lazio, Italia",
        "Info": "",
        "Conditions": "Partially cloudy"
    },
    "06/01/2009 09:00:00": {
        "Address": "Italy,Rome",
        "Date time": "06/01/2009 09:00:00",
        "Minimum Temperature": "62.9",
        "Maximum Temperature": "66.5",
        "Temperature": "65.1",
        "Dew Point": "61.0",
        "Relative Humidity": "86.8",
        "Heat Index": "",
        "Wind Speed": "18.3",
        "Wind Gust": "",
        "Wind Direction": "90.0",
        "Wind Chill": "",
        "Precipitation": "0.47",
        "Precipitation Cover": "16.67",
        "Snow Depth": "",
        "Visibility": "4.8",
        "Cloud Cover": "75.0",
        "Sea Level Pressure": "",
        "Weather Type": "",
        "Latitude": "41.9032",
        "Longitude": "12.4957",
        "Resolved Address": "Roma, Lazio, Italia",
        "Name": "Roma, Lazio, Italia",
        "Info": "",
        "Conditions": "Rain, Partially cloudy"
    },
    "06/01/2009 15:00:00": {
        "Address": "Italy,Rome",
        "Date time": "06/01/2009 15:00:00",
        "Minimum Temperature": "66.5",
        "Maximum Temperature": "71.5",
        "Temperature": "69.5",
        "Dew Point": "61.2",
        "Relative Humidity": "75.37",
        "Heat Index": "",
        "Wind Speed": "13.9",
        "Wind Gust": "",
        "Wind Direction": "114.0",
        "Wind Chill": "",
        "Precipitation": "0.0",
        "Precipitation Cover": "0.0",
        "Snow Depth": "",
        "Visibility": "6.8",
        "Cloud Cover": "51.6",
        "Sea Level Pressure": "",
        "Weather Type": "",
        "Latitude": "41.9032",
        "Longitude": "12.4957",
        "Resolved Address": "Roma, Lazio, Italia",
        "Name": "Roma, Lazio, Italia",
        "Info": "",
        "Conditions": "Partially cloudy"
    },
    "06/01/2009 21:00:00": {
        "Address": "Italy,Rome",
        "Date time": "06/01/2009 21:00:00",
        "Minimum Temperature": "62.7",
        "Maximum Temperature": "67.9",
        "Temperature": "64.1",
        "Dew Point": "59.9",
        "Relative Humidity": "86.55",
        "Heat Index": "",
        "Wind Speed": "11.4",
        "Wind Gust": "",
        "Wind Direction": "156.75",
        "Wind Chill": "",
        "Precipitation": "0.0",
        "Precipitation Cover": "0.0",
        "Snow Depth": "",
        "Visibility": "6.6",
        "Cloud Cover": "65.0",
        "Sea Level Pressure": "",
        "Weather Type": "",
        "Latitude": "41.9032",
        "Longitude": "12.4957",
        "Resolved Address": "Roma, Lazio, Italia",
        "Name": "Roma, Lazio, Italia",
        "Info": "",
        "Conditions": "Partially cloudy"
    }
}